{
    "-2":[
        [
            "oak_leaves.png",
            2
        ],
        [
            "oak_leaves.png",
            3
        ]
    ],
    "-1": [
        [
            "oak_leaves.png",
            2
        ],
        [
            "oak_leaves.png",
            3
        ],
        [
            "oak_leaves.png",
            4
        ],
        [
            "oak_leaves.png",
            5
        ]
    ],
    "0": [
        [
            "oak_log.png",
            0
        ],
        [
            "oak_log.png",
            1
        ],
        [
            "oak_log.png",
            2
        ],
        [
            "oak_log.png",
            3
        ],
        [
            "oak_leaves.png",
            4
        ],
        [
            "oak_leaves.png",
            5
        ]
    ],
    "1": [
        [
            "oak_leaves.png",
            2
        ],
        [
            "oak_leaves.png",
            3
        ],
        [
            "oak_leaves.png",
            4
        ],
        [
            "oak_leaves.png",
            5
        ]
    ],
    "2": [
        [
            "oak_leaves.png",
            2
        ],
        [
            "oak_leaves.png",
            3
        ]
    ]
}